cli_dumper/__init__.py
cli_dumper/__main__.py
cli_dumper/cli.py
cli_dumper/core.py
cli_dumper/display.py
cli_dumper-1.1.dist-info/WHEEL
cli_dumper-1.1.dist-info/entry_points.txt
cli_dumper-1.1.dist-info/METADATA
cli_dumper-1.1.dist-info/RECORD
