Metadata-Version: 2.3
Name: cli-dumper
Version: 1.1
Summary: A CLI tool that merges multiple files into a single text file
Author: DasKaroWow
Author-email: DasKaroWow <daskarowow@gmail.com>
Classifier: Development Status :: 5 - Production/Stable
Classifier: Environment :: Console
Classifier: Intended Audience :: Developers
Classifier: Intended Audience :: System Administrators
Classifier: License :: OSI Approved :: MIT License
Classifier: Operating System :: OS Independent
Classifier: Programming Language :: Python :: 3
Classifier: Programming Language :: Python :: 3 :: Only
Classifier: Programming Language :: Python :: 3.13
Classifier: Topic :: Software Development :: Build Tools
Classifier: Topic :: Utilities
Requires-Dist: rich>=14.1.0
Requires-Dist: typer>=0.16.1
Requires-Python: >=3.13
Project-URL: Homepage, https://github.com/DasKaroWow/cli-dumper
Project-URL: Issues, https://github.com/DasKaroWow/cli-dumper/issues
Project-URL: Source, https://github.com/DasKaroWow/cli-dumper
